[{"type":0,"data":{},"timestamp":1548386637288},{"type":1,"data":{},"timestamp":1548386637428},{"type":4,"data":{"href":"http://localhost:3002/","width":1680,"height":530},"timestamp":1548386637428},{"type":2,"data":{"node":{"type":0,"childNodes":[{"type":1,"name":"html","publicId":"","systemId":"","id":2},{"type":2,"tagName":"html","attributes":{"lang":"en"},"childNodes":[{"type":2,"tagName":"head","attributes":{},"childNodes":[{"type":3,"textContent":"\n  ","id":5},{"type":2,"tagName":"meta","attributes":{"charset":"UTF-8"},"childNodes":[],"id":6},{"type":3,"textContent":"\n  ","id":7},{"type":2,"tagName":"meta","attributes":{"name":"viewport","content":"width=device-width, initial-scale=1.0"},"childNodes":[],"id":8},{"type":3,"textContent":"\n  ","id":9},{"type":2,"tagName":"meta","attributes":{"http-equiv":"X-UA-Compatible","content":"ie=edge"},"childNodes":[],"id":10},{"type":3,"textContent":"\n  ","id":11},{"type":2,"tagName":"title","attributes":{},"childNodes":[{"type":3,"textContent":"test","id":13}],"id":12},{"type":3,"textContent":"\n","id":14}],"id":4},{"type":3,"textContent":"\n\n","id":15},{"type":2,"tagName":"body","attributes":{},"childNodes":[{"type":3,"textContent":"\n  ","id":17},{"type":2,"tagName":"h1","attributes":{},"childNodes":[{"type":3,"textContent":"test","id":19}],"id":18},{"type":3,"textContent":"\n  ","id":20},{"type":2,"tagName":"input","attributes":{"type":"text"},"childNodes":[],"id":21},{"type":3,"textContent":"\n  ","id":22},{"type":2,"tagName":"button","attributes":{},"childNodes":[{"type":3,"textContent":"测试","id":24}],"id":23},{"type":3,"textContent":"\n  ","id":25},{"type":2,"tagName":"button","attributes":{},"childNodes":[{"type":3,"textContent":"回放","id":27}],"id":26},{"type":3,"textContent":"\n  ","id":28},{"type":2,"tagName":"script","attributes":{"src":"http://localhost:3002/js/axios.min.js"},"childNodes":[],"id":29},{"type":3,"textContent":"\n  ","id":30},{"type":2,"tagName":"script","attributes":{"src":"http://localhost:3002/js/operationRecord.js"},"childNodes":[],"id":31},{"type":3,"textContent":"\n  ","id":32},{"type":2,"tagName":"script","attributes":{},"childNodes":[{"type":3,"textContent":"SCRIPT_PLACEHOLDER","id":34}],"id":33},{"type":2,"tagName":"div","attributes":{"title":"点击提交bug","style":"width: 40px; height: 40px; font-size: 12px; border-radius: 50%; cursor: pointer; border: 1px solid rgb(102, 102, 102); text-align: center; line-height: 40px; position: fixed; right: 20px; bottom: 20px;"},"childNodes":[{"type":3,"textContent":"提交","id":36}],"id":35},{"type":3,"textContent":"\n\n\n","id":37}],"id":16}],"id":3}],"id":1},"initialOffset":{"left":0,"top":0}},"timestamp":1548386637429},{"type":3,"data":{"source":1,"positions":[{"x":122,"y":6,"id":3,"timeOffset":0}]},"timestamp":1548386638592},{"type":3,"data":{"source":1,"positions":[{"x":143,"y":32,"id":18,"timeOffset":-479},{"x":183,"y":75,"id":16,"timeOffset":-449},{"x":231,"y":120,"id":3,"timeOffset":-414},{"x":293,"y":177,"id":3,"timeOffset":-382},{"x":324,"y":206,"id":3,"timeOffset":-348},{"x":329,"y":215,"id":3,"timeOffset":-315},{"x":317,"y":222,"id":3,"timeOffset":-281},{"x":286,"y":223,"id":3,"timeOffset":-249},{"x":286,"y":223,"id":3,"timeOffset":-75},{"x":288,"y":222,"id":3,"timeOffset":-49},{"x":293,"y":218,"id":3,"timeOffset":-16}]},"timestamp":1548386639092},{"type":3,"data":{"source":1,"positions":[{"x":290,"y":216,"id":3,"timeOffset":-483},{"x":283,"y":219,"id":3,"timeOffset":-450},{"x":279,"y":230,"id":3,"timeOffset":-417},{"x":282,"y":247,"id":3,"timeOffset":-383},{"x":307,"y":273,"id":3,"timeOffset":-350},{"x":379,"y":305,"id":3,"timeOffset":-316},{"x":520,"y":355,"id":3,"timeOffset":-283},{"x":750,"y":422,"id":3,"timeOffset":-250},{"x":1004,"y":475,"id":3,"timeOffset":-218},{"x":1222,"y":505,"id":3,"timeOffset":-184},{"x":1420,"y":510,"id":3,"timeOffset":-150},{"x":1536,"y":510,"id":3,"timeOffset":-117},{"x":1560,"y":510,"id":3,"timeOffset":-83},{"x":1566,"y":508,"id":3,"timeOffset":-50},{"x":1568,"y":506,"id":3,"timeOffset":-16}]},"timestamp":1548386639593},{"type":3,"data":{"source":1,"positions":[{"x":1569,"y":505,"id":3,"timeOffset":-483},{"x":1574,"y":503,"id":3,"timeOffset":-450},{"x":1596,"y":498,"id":3,"timeOffset":-416},{"x":1623,"y":496,"id":35,"timeOffset":-383},{"x":1636,"y":495,"id":35,"timeOffset":-350},{"x":1636,"y":495,"id":35,"timeOffset":-109},{"x":1635,"y":495,"id":35,"timeOffset":-82},{"x":1633,"y":494,"id":35,"timeOffset":-50},{"x":1632,"y":494,"id":35,"timeOffset":-17}]},"timestamp":1548386640093},{"type":3,"data":{"source":2,"type":1,"id":35,"x":1632,"y":494},"timestamp":1548386640097},{"type":3,"data":{"source":2,"type":0,"id":35,"x":1632,"y":494},"timestamp":1548386640164},{"type":3,"data":{"source":2,"type":2,"id":35,"x":1632,"y":494},"timestamp":1548386640165},{"type":3,"data":{"source":1,"positions":[{"x":1013,"y":127,"id":3,"timeOffset":0}]},"timestamp":1548386642121},{"type":3,"data":{"source":1,"positions":[{"x":912,"y":202,"id":3,"timeOffset":-415},{"x":891,"y":220,"id":3,"timeOffset":-382},{"x":883,"y":229,"id":3,"timeOffset":-348},{"x":880,"y":235,"id":3,"timeOffset":-314},{"x":879,"y":238,"id":3,"timeOffset":-281},{"x":879,"y":241,"id":3,"timeOffset":-248},{"x":879,"y":244,"id":3,"timeOffset":-214},{"x":879,"y":246,"id":3,"timeOffset":-182},{"x":879,"y":247,"id":3,"timeOffset":-147},{"x":879,"y":248,"id":3,"timeOffset":-113},{"x":879,"y":248,"id":3,"timeOffset":-81},{"x":878,"y":249,"id":3,"timeOffset":-47},{"x":878,"y":249,"id":3,"timeOffset":-13}]},"timestamp":1548386642624},{"type":3,"data":{"source":1,"positions":[{"x":878,"y":250,"id":3,"timeOffset":-483},{"x":878,"y":250,"id":3,"timeOffset":-448},{"x":878,"y":250,"id":3,"timeOffset":-260},{"x":875,"y":253,"id":3,"timeOffset":-232},{"x":866,"y":275,"id":3,"timeOffset":-198},{"x":862,"y":354,"id":3,"timeOffset":-164},{"x":918,"y":484,"id":3,"timeOffset":-133}]},"timestamp":1548386643125},{"type":3,"data":{"source":1,"positions":[{"x":1661,"y":526,"id":3,"timeOffset":0}]},"timestamp":1548386645699},{"type":3,"data":{"source":2,"type":1,"id":35,"x":1644,"y":489},"timestamp":1548386645947},{"type":3,"data":{"source":2,"type":0,"id":35,"x":1644,"y":489},"timestamp":1548386646026},{"type":3,"data":{"source":2,"type":2,"id":35,"x":1644,"y":489},"timestamp":1548386646026},{"type":3,"data":{"source":1,"positions":[{"x":1664,"y":519,"id":3,"timeOffset":-10723},{"x":1664,"y":514,"id":3,"timeOffset":-10689},{"x":1662,"y":512,"id":3,"timeOffset":-10655},{"x":1652,"y":502,"id":35,"timeOffset":-10622},{"x":1649,"y":499,"id":35,"timeOffset":-10589},{"x":1648,"y":496,"id":35,"timeOffset":-10555},{"x":1644,"y":489,"id":35,"timeOffset":-10522}]},"timestamp":1548386656449},{"type":3,"data":{"source":1,"positions":[{"x":1024,"y":117,"id":3,"timeOffset":-456},{"x":1023,"y":119,"id":3,"timeOffset":-193},{"x":1012,"y":156,"id":3,"timeOffset":-169},{"x":1000,"y":190,"id":3,"timeOffset":-141},{"x":972,"y":241,"id":3,"timeOffset":-118},{"x":923,"y":300,"id":3,"timeOffset":-84},{"x":825,"y":366,"id":3,"timeOffset":-51},{"x":761,"y":391,"id":3,"timeOffset":-15}]},"timestamp":1548386656949},{"type":3,"data":{"source":1,"positions":[{"x":679,"y":411,"id":3,"timeOffset":-488},{"x":601,"y":428,"id":3,"timeOffset":-456},{"x":530,"y":450,"id":3,"timeOffset":-421},{"x":490,"y":474,"id":3,"timeOffset":-389},{"x":464,"y":505,"id":3,"timeOffset":-356},{"x":447,"y":529,"id":3,"timeOffset":-323}]},"timestamp":1548386657453},{"type":3,"data":{"source":1,"positions":[{"x":895,"y":511,"id":3,"timeOffset":0}]},"timestamp":1548386658019},{"type":3,"data":{"source":1,"positions":[{"x":971,"y":448,"id":3,"timeOffset":-474},{"x":996,"y":421,"id":3,"timeOffset":-440},{"x":997,"y":413,"id":3,"timeOffset":-407},{"x":981,"y":398,"id":3,"timeOffset":-372},{"x":943,"y":387,"id":3,"timeOffset":-339},{"x":888,"y":393,"id":3,"timeOffset":-307},{"x":844,"y":409,"id":3,"timeOffset":-273},{"x":796,"y":435,"id":3,"timeOffset":-239},{"x":747,"y":468,"id":3,"timeOffset":-206},{"x":691,"y":496,"id":3,"timeOffset":-172},{"x":613,"y":529,"id":3,"timeOffset":-139}]},"timestamp":1548386658521},{"type":3,"data":{"source":1,"positions":[{"x":599,"y":528,"id":3,"timeOffset":-344},{"x":598,"y":525,"id":3,"timeOffset":-311},{"x":597,"y":526,"id":3,"timeOffset":-280}]},"timestamp":1548386659026},{"type":3,"data":{"source":1,"positions":[{"x":659,"y":480,"id":3,"timeOffset":0}]},"timestamp":1548386665949},{"type":3,"data":{"source":1,"positions":[{"x":605,"y":442,"id":3,"timeOffset":-484},{"x":562,"y":401,"id":3,"timeOffset":-447},{"x":568,"y":396,"id":3,"timeOffset":-417}]},"timestamp":1548386666453},{"type":3,"data":{"source":1,"positions":[{"x":575,"y":385,"id":3,"timeOffset":0}]},"timestamp":1548386681973},{"type":3,"data":{"source":1,"positions":[{"x":576,"y":385,"id":3,"timeOffset":-473},{"x":577,"y":385,"id":3,"timeOffset":-447}]},"timestamp":1548386682475},{"type":3,"data":{"source":1,"positions":[{"x":578,"y":385,"id":3,"timeOffset":-323},{"x":577,"y":386,"id":3,"timeOffset":-299},{"x":576,"y":388,"id":3,"timeOffset":-267},{"x":575,"y":393,"id":3,"timeOffset":-233},{"x":575,"y":399,"id":3,"timeOffset":-200},{"x":590,"y":430,"id":3,"timeOffset":-168},{"x":632,"y":486,"id":3,"timeOffset":-133}]},"timestamp":1548386682979},{"type":3,"data":{"source":1,"positions":[{"x":622,"y":519,"id":3,"timeOffset":0}]},"timestamp":1548386684736},{"type":3,"data":{"source":1,"positions":[{"x":955,"y":491,"id":3,"timeOffset":-474},{"x":1399,"y":453,"id":3,"timeOffset":-440},{"x":1679,"y":435,"id":3,"timeOffset":-408},{"x":1679,"y":429,"id":3,"timeOffset":-375},{"x":1679,"y":428,"id":3,"timeOffset":-342},{"x":1679,"y":428,"id":3,"timeOffset":-320},{"x":1679,"y":428,"id":3,"timeOffset":-291},{"x":1673,"y":428,"id":3,"timeOffset":-259},{"x":1672,"y":428,"id":3,"timeOffset":-224},{"x":1671,"y":432,"id":3,"timeOffset":-191},{"x":1669,"y":440,"id":3,"timeOffset":-158},{"x":1661,"y":450,"id":3,"timeOffset":-124},{"x":1645,"y":461,"id":3,"timeOffset":-91},{"x":1641,"y":463,"id":3,"timeOffset":-59},{"x":1641,"y":463,"id":3,"timeOffset":-27},{"x":1641,"y":465,"id":3,"timeOffset":-6}]},"timestamp":1548386685237},{"type":3,"data":{"source":2,"type":1,"id":35,"x":1641,"y":478},"timestamp":1548386685402},{"type":3,"data":{"source":2,"type":0,"id":35,"x":1641,"y":478},"timestamp":1548386685467},{"type":3,"data":{"source":2,"type":2,"id":35,"x":1641,"y":478},"timestamp":1548386685467}]